{
  "130": {
    "edges": [
      {
        "data": {
          "source": 59, 
          "target": 0, 
          "weight": 1.6342388155405
        }
      }, 
      {
        "data": {
          "source": 59, 
          "target": 1, 
          "weight": 0.065
        }
      }, 
      {
        "data": {
          "source": 3, 
          "target": 2, 
          "weight": 3.3984776310875002
        }
      }, 
      {
        "data": {
          "source": 59, 
          "target": 2, 
          "weight": 5.494249275749
        }
      }, 
      {
        "data": {
          "source": 4, 
          "target": 3, 
          "weight": 3.387325394193
        }
      }, 
      {
        "data": {
          "source": 5, 
          "target": 4, 
          "weight": 2.257314933991
        }
      }, 
      {
        "data": {
          "source": 60, 
          "target": 4, 
          "weight": 0.09192388155405001
        }
      }, 
      {
        "data": {
          "source": 64, 
          "target": 6, 
          "weight": 4.3800104602085
        }
      }, 
      {
        "data": {
          "source": 61, 
          "target": 7, 
          "weight": 1.8626955262175
        }
      }, 
      {
        "data": {
          "source": 63, 
          "target": 8, 
          "weight": 2.6184776310875
        }
      }, 
      {
        "data": {
          "source": 24, 
          "target": 9, 
          "weight": 11.205010460215
        }
      }, 
      {
        "data": {
          "source": 69, 
          "target": 10, 
          "weight": 8.821194077734999
        }
      }, 
      {
        "data": {
          "source": 62, 
          "target": 11, 
          "weight": 1.813467170879
        }
      }, 
      {
        "data": {
          "source": 78, 
          "target": 12, 
          "weight": 16.26656420974
        }
      }, 
      {
        "data": {
          "source": 67, 
          "target": 13, 
          "weight": 7.135020920430001
        }
      }, 
      {
        "data": {
          "source": 65, 
          "target": 14, 
          "weight": 4.8015537495315
        }
      }, 
      {
        "data": {
          "source": 105, 
          "target": 15, 
          "weight": 43.170495654454996
        }
      }, 
      {
        "data": {
          "source": 66, 
          "target": 16, 
          "weight": 5.090391052435
        }
      }, 
      {
        "data": {
          "source": 19, 
          "target": 17, 
          "weight": 1.391923881556
        }
      }, 
      {
        "data": {
          "source": 68, 
          "target": 18, 
          "weight": 0.09192388155405001
        }
      }, 
      {
        "data": {
          "source": 67, 
          "target": 19, 
          "weight": 7.810031380645
        }
      }, 
      {
        "data": {
          "source": 71, 
          "target": 19, 
          "weight": 1.04
        }
      }, 
      {
        "data": {
          "source": 68, 
          "target": 20, 
          "weight": 0.6926955262175001
        }
      }, 
      {
        "data": {
          "source": 77, 
          "target": 21, 
          "weight": 3.4050104602085
        }
      }, 
      {
        "data": {
          "source": 73, 
          "target": 22, 
          "weight": 1.4838477631055
        }
      }, 
      {
        "data": {
          "source": 84, 
          "target": 22, 
          "weight": 11.75272690683
        }
      }, 
      {
        "data": {
          "source": 71, 
          "target": 23, 
          "weight": 3.2415537495315
        }
      }, 
      {
        "data": {
          "source": 75, 
          "target": 23, 
          "weight": 33.712038943829995
        }
      }, 
      {
        "data": {
          "source": 77, 
          "target": 25, 
          "weight": 1.320391052435
        }
      }, 
      {
        "data": {
          "source": 78, 
          "target": 26, 
          "weight": 0.8496194077735001
        }
      }, 
      {
        "data": {
          "source": 74, 
          "target": 27, 
          "weight": 8.628107499050001
        }
      }, 
      {
        "data": {
          "source": 30, 
          "target": 28, 
          "weight": 1.423467170879
        }
      }, 
      {
        "data": {
          "source": 97, 
          "target": 29, 
          "weight": 19.702789668055
        }
      }, 
      {
        "data": {
          "source": 82, 
          "target": 30, 
          "weight": 2.2619343417580002
        }
      }, 
      {
        "data": {
          "source": 82, 
          "target": 31, 
          "weight": 0.52
        }
      }, 
      {
        "data": {
          "source": 93, 
          "target": 32, 
          "weight": 8.139650788359999
        }
      }, 
      {
        "data": {
          "source": 86, 
          "target": 33, 
          "weight": 2.8896298679755
        }
      }, 
      {
        "data": {
          "source": 87, 
          "target": 34, 
          "weight": 2.8246298679755
        }
      }, 
      {
        "data": {
          "source": 90, 
          "target": 34, 
          "weight": 4.084640328184
        }
      }, 
      {
        "data": {
          "source": 89, 
          "target": 35, 
          "weight": 1.611934341758
        }
      }, 
      {
        "data": {
          "source": 88, 
          "target": 36, 
          "weight": 0.7957716446615
        }
      }, 
      {
        "data": {
          "source": 99, 
          "target": 37, 
          "weight": 11.59118361752
        }
      }, 
      {
        "data": {
          "source": 91, 
          "target": 38, 
          "weight": 1.0176955262175
        }
      }, 
      {
        "data": {
          "source": 98, 
          "target": 39, 
          "weight": 1.5376955262175
        }
      }, 
      {
        "data": {
          "source": 103, 
          "target": 41, 
          "weight": 1.5376955262175
        }
      }, 
      {
        "data": {
          "source": 104, 
          "target": 42, 
          "weight": 3.2750104602085
        }
      }, 
      {
        "data": {
          "source": 108, 
          "target": 43, 
          "weight": 0.9034671708790001
        }
      }, 
      {
        "data": {
          "source": 109, 
          "target": 44, 
          "weight": 3.7234776310875004
        }
      }, 
      {
        "data": {
          "source": 111, 
          "target": 45, 
          "weight": 1.7800104602085
        }
      }, 
      {
        "data": {
          "source": 112, 
          "target": 46, 
          "weight": 0.63884776310875
        }
      }, 
      {
        "data": {
          "source": 117, 
          "target": 47, 
          "weight": 1.4550104602085001
        }
      }, 
      {
        "data": {
          "source": 50, 
          "target": 48, 
          "weight": 0.65
        }
      }, 
      {
        "data": {
          "source": 120, 
          "target": 49, 
          "weight": 0.5515432893256
        }
      }, 
      {
        "data": {
          "source": 119, 
          "target": 51, 
          "weight": 4.362325394193
        }
      }, 
      {
        "data": {
          "source": 122, 
          "target": 52, 
          "weight": 2.1542388155405
        }
      }, 
      {
        "data": {
          "source": 121, 
          "target": 53, 
          "weight": 11.30234631461
        }
      }, 
      {
        "data": {
          "source": 123, 
          "target": 54, 
          "weight": 6.1292701961595
        }
      }, 
      {
        "data": {
          "source": 116, 
          "target": 55, 
          "weight": 30.701319600185002
        }
      }, 
      {
        "data": {
          "source": 122, 
          "target": 56, 
          "weight": 16.407716446615
        }
      }, 
      {
        "data": {
          "source": 123, 
          "target": 57, 
          "weight": 17.995104602085004
        }
      }, 
      {
        "data": {
          "source": 121, 
          "target": 58, 
          "weight": 30.12285242928
        }
      }, 
      {
        "data": {
          "source": 62, 
          "target": 61, 
          "weight": 1.6026955262175
        }
      }, 
      {
        "data": {
          "source": 63, 
          "target": 61, 
          "weight": 2.333467170879
        }
      }, 
      {
        "data": {
          "source": 64, 
          "target": 62, 
          "weight": 2.3046298679755
        }
      }, 
      {
        "data": {
          "source": 67, 
          "target": 63, 
          "weight": 8.19620453795
        }
      }, 
      {
        "data": {
          "source": 73, 
          "target": 64, 
          "weight": 5.285391052435
        }
      }, 
      {
        "data": {
          "source": 66, 
          "target": 65, 
          "weight": 0.6657716446615
        }
      }, 
      {
        "data": {
          "source": 76, 
          "target": 65, 
          "weight": 6.416194077715501
        }
      }, 
      {
        "data": {
          "source": 80, 
          "target": 66, 
          "weight": 13.041574669955
        }
      }, 
      {
        "data": {
          "source": 72, 
          "target": 67, 
          "weight": 1.261923881556
        }
      }, 
      {
        "data": {
          "source": 75, 
          "target": 67, 
          "weight": 3.9769448019665004
        }
      }, 
      {
        "data": {
          "source": 70, 
          "target": 68, 
          "weight": 0.52461940777155
        }
      }, 
      {
        "data": {
          "source": 71, 
          "target": 68, 
          "weight": 2.7596298679755003
        }
      }, 
      {
        "data": {
          "source": 70, 
          "target": 69, 
          "weight": 0.7150000000000001
        }
      }, 
      {
        "data": {
          "source": 74, 
          "target": 69, 
          "weight": 2.4838582233140003
        }
      }, 
      {
        "data": {
          "source": 83, 
          "target": 70, 
          "weight": 14.801986642755
        }
      }, 
      {
        "data": {
          "source": 75, 
          "target": 72, 
          "weight": 3.2146298679755003
        }
      }, 
      {
        "data": {
          "source": 77, 
          "target": 72, 
          "weight": 2.645401512637
        }
      }, 
      {
        "data": {
          "source": 75, 
          "target": 73, 
          "weight": 9.80002092043
        }
      }, 
      {
        "data": {
          "source": 76, 
          "target": 74, 
          "weight": 3.6380865786525
        }
      }, 
      {
        "data": {
          "source": 79, 
          "target": 76, 
          "weight": 7.859259735925
        }
      }, 
      {
        "data": {
          "source": 86, 
          "target": 78, 
          "weight": 7.10888960392
        }
      }, 
      {
        "data": {
          "source": 80, 
          "target": 79, 
          "weight": 1.7438477631055
        }
      }, 
      {
        "data": {
          "source": 81, 
          "target": 79, 
          "weight": 2.4857716446615
        }
      }, 
      {
        "data": {
          "source": 86, 
          "target": 80, 
          "weight": 18.807768747624998
        }
      }, 
      {
        "data": {
          "source": 83, 
          "target": 81, 
          "weight": 11.322737367045
        }
      }, 
      {
        "data": {
          "source": 89, 
          "target": 81, 
          "weight": 10.061606050535
        }
      }, 
      {
        "data": {
          "source": 85, 
          "target": 82, 
          "weight": 0.941543289323
        }
      }, 
      {
        "data": {
          "source": 85, 
          "target": 83, 
          "weight": 0.708467170879
        }
      }, 
      {
        "data": {
          "source": 87, 
          "target": 84, 
          "weight": 4.653868683516
        }
      }, 
      {
        "data": {
          "source": 88, 
          "target": 84, 
          "weight": 5.9854119728455
        }
      }, 
      {
        "data": {
          "source": 95, 
          "target": 85, 
          "weight": 11.448117959265002
        }
      }, 
      {
        "data": {
          "source": 92, 
          "target": 87, 
          "weight": 8.958519471915
        }
      }, 
      {
        "data": {
          "source": 90, 
          "target": 88, 
          "weight": 3.086543289323
        }
      }, 
      {
        "data": {
          "source": 94, 
          "target": 89, 
          "weight": 5.8108030252805
        }
      }, 
      {
        "data": {
          "source": 91, 
          "target": 90, 
          "weight": 1.0557716446615
        }
      }, 
      {
        "data": {
          "source": 98, 
          "target": 91, 
          "weight": 4.238858223314
        }
      }, 
      {
        "data": {
          "source": 96, 
          "target": 92, 
          "weight": 6.9158030253
        }
      }, 
      {
        "data": {
          "source": 106, 
          "target": 92, 
          "weight": 15.613529932130001
        }
      }, 
      {
        "data": {
          "source": 95, 
          "target": 93, 
          "weight": 5.3550104602085
        }
      }, 
      {
        "data": {
          "source": 100, 
          "target": 93, 
          "weight": 11.04043289323
        }
      }, 
      {
        "data": {
          "source": 97, 
          "target": 94, 
          "weight": 4.8311836175069995
        }
      }, 
      {
        "data": {
          "source": 116, 
          "target": 94, 
          "weight": 42.875918087535005
        }
      }, 
      {
        "data": {
          "source": 96, 
          "target": 95, 
          "weight": 5.765401512637
        }
      }, 
      {
        "data": {
          "source": 101, 
          "target": 96, 
          "weight": 3.6984671708790002
        }
      }, 
      {
        "data": {
          "source": 102, 
          "target": 97, 
          "weight": 6.611194077735
        }
      }, 
      {
        "data": {
          "source": 104, 
          "target": 98, 
          "weight": 5.830401512637
        }
      }, 
      {
        "data": {
          "source": 102, 
          "target": 99, 
          "weight": 1.8673149339910002
        }
      }, 
      {
        "data": {
          "source": 103, 
          "target": 100, 
          "weight": 5.9269448019665
        }
      }, 
      {
        "data": {
          "source": 111, 
          "target": 100, 
          "weight": 21.101246378745003
        }
      }, 
      {
        "data": {
          "source": 103, 
          "target": 101, 
          "weight": 13.82810749905
        }
      }, 
      {
        "data": {
          "source": 107, 
          "target": 101, 
          "weight": 10.20929111657
        }
      }, 
      {
        "data": {
          "source": 105, 
          "target": 102, 
          "weight": 3.4680970388545003
        }
      }, 
      {
        "data": {
          "source": 114, 
          "target": 104, 
          "weight": 25.49352993213
        }
      }, 
      {
        "data": {
          "source": 108, 
          "target": 105, 
          "weight": 6.1869448019665
        }
      }, 
      {
        "data": {
          "source": 107, 
          "target": 106, 
          "weight": 0.9146194077735
        }
      }, 
      {
        "data": {
          "source": 109, 
          "target": 106, 
          "weight": 4.9119552621685
        }
      }, 
      {
        "data": {
          "source": 110, 
          "target": 107, 
          "weight": 5.1338791437245
        }
      }, 
      {
        "data": {
          "source": 119, 
          "target": 108, 
          "weight": 31.43736723504
        }
      }, 
      {
        "data": {
          "source": 110, 
          "target": 109, 
          "weight": 0.892314933991
        }
      }, 
      {
        "data": {
          "source": 113, 
          "target": 110, 
          "weight": 16.06120453795
        }
      }, 
      {
        "data": {
          "source": 115, 
          "target": 111, 
          "weight": 10.840813485515
        }
      }, 
      {
        "data": {
          "source": 113, 
          "target": 112, 
          "weight": 1.0557716446615
        }
      }, 
      {
        "data": {
          "source": 114, 
          "target": 112, 
          "weight": 0.9796194077735001
        }
      }, 
      {
        "data": {
          "source": 120, 
          "target": 113, 
          "weight": 14.47348809127
        }
      }, 
      {
        "data": {
          "source": 118, 
          "target": 114, 
          "weight": 12.969249275774999
        }
      }, 
      {
        "data": {
          "source": 116, 
          "target": 115, 
          "weight": 8.21388960392
        }
      }, 
      {
        "data": {
          "source": 117, 
          "target": 115, 
          "weight": 9.343900064135001
        }
      }, 
      {
        "data": {
          "source": 121, 
          "target": 117, 
          "weight": 9.81737769519
        }
      }, 
      {
        "data": {
          "source": 123, 
          "target": 119, 
          "weight": 13.86314933991
        }
      }, 
      {
        "data": {
          "source": 122, 
          "target": 120, 
          "weight": 7.403467170905
        }
      }
    ], 
    "nodes": [
      {
        "data": {
          "id": 0
        }, 
        "position": {
          "x": 270.0, 
          "y": 131.0
        }
      }, 
      {
        "data": {
          "id": 1
        }, 
        "position": {
          "x": 254.0, 
          "y": 154.0
        }
      }, 
      {
        "data": {
          "id": 2
        }, 
        "position": {
          "x": 171.0, 
          "y": 176.0
        }
      }, 
      {
        "data": {
          "id": 3
        }, 
        "position": {
          "x": 128.0, 
          "y": 191.0
        }
      }, 
      {
        "data": {
          "id": 4
        }, 
        "position": {
          "x": 80.0, 
          "y": 216.0
        }
      }, 
      {
        "data": {
          "id": 5
        }, 
        "position": {
          "x": 59.0, 
          "y": 221.0
        }
      }, 
      {
        "data": {
          "id": 6
        }, 
        "position": {
          "x": 12.0, 
          "y": 400.0
        }
      }, 
      {
        "data": {
          "id": 7
        }, 
        "position": {
          "x": 78.0, 
          "y": 406.0
        }
      }, 
      {
        "data": {
          "id": 8
        }, 
        "position": {
          "x": 132.0, 
          "y": 408.0
        }
      }, 
      {
        "data": {
          "id": 9
        }, 
        "position": {
          "x": 859.0, 
          "y": 408.0
        }
      }, 
      {
        "data": {
          "id": 10
        }, 
        "position": {
          "x": 425.0, 
          "y": 410.0
        }
      }, 
      {
        "data": {
          "id": 11
        }, 
        "position": {
          "x": 41.0, 
          "y": 413.0
        }
      }, 
      {
        "data": {
          "id": 12
        }, 
        "position": {
          "x": 833.0, 
          "y": 413.0
        }
      }, 
      {
        "data": {
          "id": 13
        }, 
        "position": {
          "x": 238.0, 
          "y": 417.0
        }
      }, 
      {
        "data": {
          "id": 14
        }, 
        "position": {
          "x": 497.0, 
          "y": 417.0
        }
      }, 
      {
        "data": {
          "id": 15
        }, 
        "position": {
          "x": 879.0, 
          "y": 427.0
        }
      }, 
      {
        "data": {
          "id": 16
        }, 
        "position": {
          "x": 603.0, 
          "y": 495.0
        }
      }, 
      {
        "data": {
          "id": 17
        }, 
        "position": {
          "x": 315.0, 
          "y": 497.0
        }
      }, 
      {
        "data": {
          "id": 18
        }, 
        "position": {
          "x": 356.0, 
          "y": 517.0
        }
      }, 
      {
        "data": {
          "id": 19
        }, 
        "position": {
          "x": 319.0, 
          "y": 519.0
        }
      }, 
      {
        "data": {
          "id": 20
        }, 
        "position": {
          "x": 340.0, 
          "y": 519.0
        }
      }, 
      {
        "data": {
          "id": 21
        }, 
        "position": {
          "x": 279.0, 
          "y": 555.0
        }
      }, 
      {
        "data": {
          "id": 22
        }, 
        "position": {
          "x": 8.0, 
          "y": 567.0
        }
      }, 
      {
        "data": {
          "id": 23
        }, 
        "position": {
          "x": 288.0, 
          "y": 576.0
        }
      }, 
      {
        "data": {
          "id": 24
        }, 
        "position": {
          "x": 859.0, 
          "y": 576.0
        }
      }, 
      {
        "data": {
          "id": 25
        }, 
        "position": {
          "x": 221.0, 
          "y": 586.0
        }
      }, 
      {
        "data": {
          "id": 26
        }, 
        "position": {
          "x": 848.0, 
          "y": 658.0
        }
      }, 
      {
        "data": {
          "id": 27
        }, 
        "position": {
          "x": 440.0, 
          "y": 665.0
        }
      }, 
      {
        "data": {
          "id": 28
        }, 
        "position": {
          "x": 295.0, 
          "y": 684.0
        }
      }, 
      {
        "data": {
          "id": 29
        }, 
        "position": {
          "x": 844.0, 
          "y": 684.0
        }
      }, 
      {
        "data": {
          "id": 30
        }, 
        "position": {
          "x": 311.0, 
          "y": 701.0
        }
      }, 
      {
        "data": {
          "id": 31
        }, 
        "position": {
          "x": 325.0, 
          "y": 716.0
        }
      }, 
      {
        "data": {
          "id": 32
        }, 
        "position": {
          "x": 461.0, 
          "y": 771.0
        }
      }, 
      {
        "data": {
          "id": 33
        }, 
        "position": {
          "x": 798.0, 
          "y": 775.0
        }
      }, 
      {
        "data": {
          "id": 34
        }, 
        "position": {
          "x": 47.0, 
          "y": 807.0
        }
      }, 
      {
        "data": {
          "id": 35
        }, 
        "position": {
          "x": 611.0, 
          "y": 809.0
        }
      }, 
      {
        "data": {
          "id": 36
        }, 
        "position": {
          "x": 28.0, 
          "y": 815.0
        }
      }, 
      {
        "data": {
          "id": 37
        }, 
        "position": {
          "x": 831.0, 
          "y": 830.0
        }
      }, 
      {
        "data": {
          "id": 38
        }, 
        "position": {
          "x": 6.0, 
          "y": 888.0
        }
      }, 
      {
        "data": {
          "id": 39
        }, 
        "position": {
          "x": 9.0, 
          "y": 904.0
        }
      }, 
      {
        "data": {
          "id": 40
        }, 
        "position": {
          "x": 803.0, 
          "y": 962.0
        }
      }, 
      {
        "data": {
          "id": 41
        }, 
        "position": {
          "x": 472.0, 
          "y": 973.0
        }
      }, 
      {
        "data": {
          "id": 42
        }, 
        "position": {
          "x": 86.0, 
          "y": 992.0
        }
      }, 
      {
        "data": {
          "id": 43
        }, 
        "position": {
          "x": 854.0, 
          "y": 1101.0
        }
      }, 
      {
        "data": {
          "id": 44
        }, 
        "position": {
          "x": 86.0, 
          "y": 1170.0
        }
      }, 
      {
        "data": {
          "id": 45
        }, 
        "position": {
          "x": 674.0, 
          "y": 1250.0
        }
      }, 
      {
        "data": {
          "id": 46
        }, 
        "position": {
          "x": 41.0, 
          "y": 1347.0
        }
      }, 
      {
        "data": {
          "id": 47
        }, 
        "position": {
          "x": 543.0, 
          "y": 1505.0
        }
      }, 
      {
        "data": {
          "id": 48
        }, 
        "position": {
          "x": 3.0, 
          "y": 1560.0
        }
      }, 
      {
        "data": {
          "id": 49
        }, 
        "position": {
          "x": 21.0, 
          "y": 1565.0
        }
      }, 
      {
        "data": {
          "id": 50
        }, 
        "position": {
          "x": 7.0, 
          "y": 1568.0
        }
      }, 
      {
        "data": {
          "id": 51
        }, 
        "position": {
          "x": 885.0, 
          "y": 1620.0
        }
      }, 
      {
        "data": {
          "id": 52
        }, 
        "position": {
          "x": 7.0, 
          "y": 1662.0
        }
      }, 
      {
        "data": {
          "id": 53
        }, 
        "position": {
          "x": 472.0, 
          "y": 1752.0
        }
      }, 
      {
        "data": {
          "id": 54
        }, 
        "position": {
          "x": 809.0, 
          "y": 1814.0
        }
      }, 
      {
        "data": {
          "id": 55
        }, 
        "position": {
          "x": 431.0, 
          "y": 1823.0
        }
      }, 
      {
        "data": {
          "id": 56
        }, 
        "position": {
          "x": 0.0, 
          "y": 1925.0
        }
      }, 
      {
        "data": {
          "id": 57
        }, 
        "position": {
          "x": 621.0, 
          "y": 1957.0
        }
      }, 
      {
        "data": {
          "id": 58
        }, 
        "position": {
          "x": 247.0, 
          "y": 1972.0
        }
      }, 
      {
        "data": {
          "id": 59
        }, 
        "position": {
          "x": 249.0, 
          "y": 148.0
        }
      }, 
      {
        "data": {
          "id": 60
        }, 
        "position": {
          "x": 84.0, 
          "y": 221.0
        }
      }, 
      {
        "data": {
          "id": 61
        }, 
        "position": {
          "x": 75.0, 
          "y": 434.0
        }
      }, 
      {
        "data": {
          "id": 62
        }, 
        "position": {
          "x": 49.0, 
          "y": 439.0
        }
      }, 
      {
        "data": {
          "id": 63
        }, 
        "position": {
          "x": 111.0, 
          "y": 441.0
        }
      }, 
      {
        "data": {
          "id": 64
        }, 
        "position": {
          "x": 23.0, 
          "y": 462.0
        }
      }, 
      {
        "data": {
          "id": 65
        }, 
        "position": {
          "x": 516.0, 
          "y": 483.0
        }
      }, 
      {
        "data": {
          "id": 66
        }, 
        "position": {
          "x": 527.0, 
          "y": 488.0
        }
      }, 
      {
        "data": {
          "id": 67
        }, 
        "position": {
          "x": 206.0, 
          "y": 513.0
        }
      }, 
      {
        "data": {
          "id": 68
        }, 
        "position": {
          "x": 354.0, 
          "y": 523.0
        }
      }, 
      {
        "data": {
          "id": 69
        }, 
        "position": {
          "x": 373.0, 
          "y": 530.0
        }
      }, 
      {
        "data": {
          "id": 70
        }, 
        "position": {
          "x": 359.0, 
          "y": 531.0
        }
      }, 
      {
        "data": {
          "id": 71
        }, 
        "position": {
          "x": 315.0, 
          "y": 538.0
        }
      }, 
      {
        "data": {
          "id": 72
        }, 
        "position": {
          "x": 201.0, 
          "y": 539.0
        }
      }, 
      {
        "data": {
          "id": 73
        }, 
        "position": {
          "x": 14.0, 
          "y": 541.0
        }
      }, 
      {
        "data": {
          "id": 74
        }, 
        "position": {
          "x": 406.0, 
          "y": 548.0
        }
      }, 
      {
        "data": {
          "id": 75
        }, 
        "position": {
          "x": 155.0, 
          "y": 551.0
        }
      }, 
      {
        "data": {
          "id": 76
        }, 
        "position": {
          "x": 461.0, 
          "y": 560.0
        }
      }, 
      {
        "data": {
          "id": 77
        }, 
        "position": {
          "x": 230.0, 
          "y": 567.0
        }
      }, 
      {
        "data": {
          "id": 78
        }, 
        "position": {
          "x": 836.0, 
          "y": 651.0
        }
      }, 
      {
        "data": {
          "id": 79
        }, 
        "position": {
          "x": 501.0, 
          "y": 666.0
        }
      }, 
      {
        "data": {
          "id": 80
        }, 
        "position": {
          "x": 530.0, 
          "y": 668.0
        }
      }, 
      {
        "data": {
          "id": 81
        }, 
        "position": {
          "x": 501.0, 
          "y": 706.0
        }
      }, 
      {
        "data": {
          "id": 82
        }, 
        "position": {
          "x": 326.0, 
          "y": 725.0
        }
      }, 
      {
        "data": {
          "id": 83
        }, 
        "position": {
          "x": 348.0, 
          "y": 728.0
        }
      }, 
      {
        "data": {
          "id": 84
        }, 
        "position": {
          "x": 52.0, 
          "y": 732.0
        }
      }, 
      {
        "data": {
          "id": 85
        }, 
        "position": {
          "x": 336.0, 
          "y": 737.0
        }
      }, 
      {
        "data": {
          "id": 86
        }, 
        "position": {
          "x": 778.0, 
          "y": 738.0
        }
      }, 
      {
        "data": {
          "id": 87
        }, 
        "position": {
          "x": 85.0, 
          "y": 789.0
        }
      }, 
      {
        "data": {
          "id": 88
        }, 
        "position": {
          "x": 15.0, 
          "y": 811.0
        }
      }, 
      {
        "data": {
          "id": 89
        }, 
        "position": {
          "x": 590.0, 
          "y": 824.0
        }
      }, 
      {
        "data": {
          "id": 90
        }, 
        "position": {
          "x": 13.0, 
          "y": 857.0
        }
      }, 
      {
        "data": {
          "id": 91
        }, 
        "position": {
          "x": 12.0, 
          "y": 873.0
        }
      }, 
      {
        "data": {
          "id": 92
        }, 
        "position": {
          "x": 185.0, 
          "y": 873.0
        }
      }, 
      {
        "data": {
          "id": 93
        }, 
        "position": {
          "x": 435.0, 
          "y": 879.0
        }
      }, 
      {
        "data": {
          "id": 94
        }, 
        "position": {
          "x": 648.0, 
          "y": 884.0
        }
      }, 
      {
        "data": {
          "id": 95
        }, 
        "position": {
          "x": 356.0, 
          "y": 893.0
        }
      }, 
      {
        "data": {
          "id": 96
        }, 
        "position": {
          "x": 275.0, 
          "y": 916.0
        }
      }, 
      {
        "data": {
          "id": 97
        }, 
        "position": {
          "x": 709.0, 
          "y": 922.0
        }
      }, 
      {
        "data": {
          "id": 98
        }, 
        "position": {
          "x": 13.0, 
          "y": 925.0
        }
      }, 
      {
        "data": {
          "id": 99
        }, 
        "position": {
          "x": 808.0, 
          "y": 969.0
        }
      }, 
      {
        "data": {
          "id": 100
        }, 
        "position": {
          "x": 552.0, 
          "y": 971.0
        }
      }, 
      {
        "data": {
          "id": 101
        }, 
        "position": {
          "x": 270.0, 
          "y": 972.0
        }
      }, 
      {
        "data": {
          "id": 102
        }, 
        "position": {
          "x": 784.0, 
          "y": 982.0
        }
      }, 
      {
        "data": {
          "id": 103
        }, 
        "position": {
          "x": 469.0, 
          "y": 996.0
        }
      }, 
      {
        "data": {
          "id": 104
        }, 
        "position": {
          "x": 38.0, 
          "y": 1006.0
        }
      }, 
      {
        "data": {
          "id": 105
        }, 
        "position": {
          "x": 813.0, 
          "y": 1025.0
        }
      }, 
      {
        "data": {
          "id": 106
        }, 
        "position": {
          "x": 167.0, 
          "y": 1077.0
        }
      }, 
      {
        "data": {
          "id": 107
        }, 
        "position": {
          "x": 178.0, 
          "y": 1086.0
        }
      }, 
      {
        "data": {
          "id": 108
        }, 
        "position": {
          "x": 842.0, 
          "y": 1110.0
        }
      }, 
      {
        "data": {
          "id": 109
        }, 
        "position": {
          "x": 114.0, 
          "y": 1127.0
        }
      }, 
      {
        "data": {
          "id": 110
        }, 
        "position": {
          "x": 124.0, 
          "y": 1138.0
        }
      }, 
      {
        "data": {
          "id": 111
        }, 
        "position": {
          "x": 656.0, 
          "y": 1230.0
        }
      }, 
      {
        "data": {
          "id": 112
        }, 
        "position": {
          "x": 44.0, 
          "y": 1356.0
        }
      }, 
      {
        "data": {
          "id": 113
        }, 
        "position": {
          "x": 61.0, 
          "y": 1361.0
        }
      }, 
      {
        "data": {
          "id": 114
        }, 
        "position": {
          "x": 28.0, 
          "y": 1364.0
        }
      }, 
      {
        "data": {
          "id": 115
        }, 
        "position": {
          "x": 599.0, 
          "y": 1376.0
        }
      }, 
      {
        "data": {
          "id": 116
        }, 
        "position": {
          "x": 669.0, 
          "y": 1466.0
        }
      }, 
      {
        "data": {
          "id": 117
        }, 
        "position": {
          "x": 527.0, 
          "y": 1489.0
        }
      }, 
      {
        "data": {
          "id": 118
        }, 
        "position": {
          "x": 9.0, 
          "y": 1556.0
        }
      }, 
      {
        "data": {
          "id": 119
        }, 
        "position": {
          "x": 856.0, 
          "y": 1565.0
        }
      }, 
      {
        "data": {
          "id": 120
        }, 
        "position": {
          "x": 27.0, 
          "y": 1571.0
        }
      }, 
      {
        "data": {
          "id": 121
        }, 
        "position": {
          "x": 432.0, 
          "y": 1598.0
        }
      }, 
      {
        "data": {
          "id": 122
        }, 
        "position": {
          "x": 24.0, 
          "y": 1684.0
        }
      }, 
      {
        "data": {
          "id": 123
        }, 
        "position": {
          "x": 759.0, 
          "y": 1738.0
        }
      }
    ]
  }
}
